ccaerrors/__init__.py
ccaerrors-0.1.2.dist-info/LICENSE
ccaerrors-0.1.2.dist-info/WHEEL
ccaerrors-0.1.2.dist-info/METADATA
ccaerrors-0.1.2.dist-info/RECORD
