Metadata-Version: 2.1
Name: ccaerrors
Version: 0.1.2
Summary: universal error handling for python functions.
Home-page: https://github.com/ccdale/ccaerrors.git
License: GPL-3.0-or-later
Author: ccdale
Author-email: chris.charles.allison+ccaerrors@gmail.com
Requires-Python: >=3.10,<4.0
Classifier: License :: OSI Approved :: GNU General Public License v3 or later (GPLv3+)
Classifier: Programming Language :: Python :: 3
Classifier: Programming Language :: Python :: 3.10
Project-URL: Repository, https://github.com/ccdale/ccaerrors.git
